piptuf_demo/demo.py
piptuf_demo-0.2.dist-info/METADATA
piptuf_demo-0.2.dist-info/WHEEL
piptuf_demo-0.2.dist-info/top_level.txt
piptuf_demo-0.2.dist-info/RECORD
