Metadata-Version: 2.1
Name: piptuf-demo
Version: 0.2
Summary: A demo project.
Home-page: UNKNOWN
Author: LV
Author-email: lv@example.com
License: UNKNOWN
Platform: UNKNOWN
Classifier: Programming Language :: Python :: 3
Classifier: License :: OSI Approved :: MIT License
Classifier: Operating System :: OS Independent
Requires-Python: >=3.6
